comun_va.py
comun_va-3.9.dist-info/METADATA
comun_va-3.9.dist-info/WHEEL
comun_va-3.9.dist-info/top_level.txt
comun_va-3.9.dist-info/RECORD
