Metadata-Version: 2.1
Name: comun-va
Version: 3.9
Requires-Dist: comun-sqlsrv
Requires-Dist: opencv-python
Requires-Dist: tensorflow
Requires-Dist: numpy
Requires-Dist: pyzbar
